simpler_devops_api/__init__.py
simpler_devops_api/base.py
simpler_devops_api/devops_config.py
simpler_devops_api/policy.py
simpler_devops_api/policy_types.py
simpler_devops_api/policybuilder.py
simpler_devops_api/projects.py
simpler_devops_api/repos.py
simpler_devops_api-0.2.20190514.2.dist-info/METADATA
simpler_devops_api-0.2.20190514.2.dist-info/WHEEL
simpler_devops_api-0.2.20190514.2.dist-info/top_level.txt
simpler_devops_api-0.2.20190514.2.dist-info/RECORD
