Metadata-Version: 2.1
Name: simpler-devops-api
Version: 0.2.20190514.2
Summary: A Simpler Python Module for interacting with Azure Devops
Home-page: https://dev.azure.com/JonTruran/python-devops/
Author: Jon Truran
Author-email: jontruran@paypoint.com
License: UNKNOWN
Platform: UNKNOWN
Classifier: Programming Language :: Python :: 3
Classifier: License :: OSI Approved :: MIT License
Classifier: Operating System :: OS Independent
Requires-Dist: fuzzywuzzy
Requires-Dist: azure-devops
Requires-Dist: appdirs
Requires-Dist: configparser
